fastapi_redis_utils/__init__.py
fastapi_redis_utils/dependency.py
fastapi_redis_utils/exceptions.py
fastapi_redis_utils/manager.py
fastapi_redis_utils/models.py
fastapi_redis_utils/py.typed
fastapi_redis_utils/repository.py
fastapi_redis_utils/utils.py
fastapi_redis_utils-2.0.9.dist-info/METADATA
fastapi_redis_utils-2.0.9.dist-info/WHEEL
fastapi_redis_utils-2.0.9.dist-info/licenses/LICENSE
fastapi_redis_utils-2.0.9.dist-info/RECORD
