Metadata-Version: 2.4
Name: fastapi-redis-utils
Version: 2.0.9
Summary: Fast and easy Redis integration for FastAPI applications.
Project-URL: Homepage, https://github.com/serafinovsky/fastapi-redis-utils
Project-URL: Documentation, https://github.com/serafinovsky/fastapi-redis-utils#readme
Project-URL: Repository, https://github.com/serafinovsky/fastapi-redis-utils
Project-URL: Issues, https://github.com/serafinovsky/fastapi-redis-utils/issues
Author-email: Mark Serafinovsky <m.serafinovsky@gmail.com>
License: MIT
License-File: LICENSE
Keywords: async,connection-pool,dependency-injection,fastapi,redis,utils
Classifier: Development Status :: 5 - Production/Stable
Classifier: Framework :: FastAPI
Classifier: Intended Audience :: Developers
Classifier: License :: OSI Approved :: MIT License
Classifier: Operating System :: OS Independent
Classifier: Programming Language :: Python :: 3
Classifier: Programming Language :: Python :: 3.11
Classifier: Programming Language :: Python :: 3.12
Classifier: Programming Language :: Python :: 3.13
Classifier: Topic :: Database
Classifier: Topic :: Software Development :: Libraries :: Python Modules
Classifier: Typing :: Typed
Requires-Python: >=3.11
Requires-Dist: pydantic<3,>=2.11
Requires-Dist: redis<8,>=6.4
